Dmail/__init__.py
Dmail/email_.py
Dmail/email_base.py
Dmail/simple_email.py
Dmail/api/__init__.py
Dmail/api/_gmail_api_base.py
Dmail/api/gmail_api.py
Dmail/esp/__init__.py
Dmail/esp/gmail.py
Dmail/esp/hotmail.py
Dmail/esp/office365.py
Dmail/esp/yahoo.py
Dmail/mixin/__init__.py
Dmail/mixin/email_base.py
Dmail/mixin/html_mixin.py
Dmail/mixin/markdown_mixin.py
Dmail/mixin/mime_base_mixin.py
Dmail/mixin/mime_mixin.py
Dmail/mixin/smtp_mixin.py
Dmail/styles/default.css
Dmail-1.3.0.dist-info/LICENSE
Dmail-1.3.0.dist-info/METADATA
Dmail-1.3.0.dist-info/WHEEL
Dmail-1.3.0.dist-info/top_level.txt
Dmail-1.3.0.dist-info/RECORD
