Metadata-Version: 2.1
Name: Dmail
Version: 1.3.0
Summary: This is a simple package that provides a quick way to send emails through code.
Home-page: https://github.com/hmiladhia/Dmail
Author: Dhia Hmila
Author-email: hmiladhia@hotmail.fr
License: UNKNOWN
Keywords: email mail markdown md html style css
Platform: UNKNOWN
Classifier: Programming Language :: Python :: 3
Classifier: License :: OSI Approved :: MIT License
Classifier: Operating System :: OS Independent
Requires-Python: >= 3.6
Requires-Dist: markdown
Requires-Dist: html2text
Requires-Dist: premailer
Provides-Extra: codehighlight
Requires-Dist: Pygments ; extra == 'codehighlight'
Provides-Extra: gmailapi
Requires-Dist: google-api-python-client ; extra == 'gmailapi'
Requires-Dist: google-auth-httplib2 ; extra == 'gmailapi'
Requires-Dist: google-auth-oauthlib ; extra == 'gmailapi'
